open_spex/BGMeasurement.py
open_spex/BGSample.py
open_spex/__init__.py
open_spex/aboutMessage.py
open_spex/bgm.py
open_spex/const.py
open_spex/dialogs.py
open_spex/helpOpenSpex.py
open_spex/histPlotBox.py
open_spex/main.py
open_spex/measurementPanel.py
open_spex/menu.py
open_spex/optionsPanel.py
open_spex/plotPanel.py
open_spex/utils.py
open_spex/version.py
open_spex/xenonSampleSet.py
open_spex-1.0.7.dist-info/LICENSE
open_spex-1.0.7.dist-info/METADATA
open_spex-1.0.7.dist-info/WHEEL
open_spex-1.0.7.dist-info/entry_points.txt
open_spex-1.0.7.dist-info/top_level.txt
open_spex-1.0.7.dist-info/RECORD
