Metadata-Version: 2.1
Name: open-spex
Version: 1.0.7
Summary: Radioxenon beta-gamma analysis tool
Home-page: UNKNOWN
Author: Anders Ringbom
Author-email: anders.ringbom@foi.se
License: UNKNOWN
Platform: UNKNOWN
Classifier: Programming Language :: Python :: 3
Classifier: License :: OSI Approved :: MIT License
Classifier: Operating System :: OS Independent
Requires-Python: >=3.6.9
Requires-Dist: wheel
Requires-Dist: matplotlib
Requires-Dist: numpy
Requires-Dist: scipy
Requires-Dist: wxpython
